plone.app.testing-7.1.2-py3.13-nspkg.pth
plone/app/testing/__init__.py
plone/app/testing/bbb.py
plone/app/testing/cleanup.py
plone/app/testing/cleanup.rst
plone/app/testing/helpers.py
plone/app/testing/helpers.rst
plone/app/testing/interfaces.py
plone/app/testing/layers.py
plone/app/testing/layers.rst
plone/app/testing/selenium.rst
plone/app/testing/selenium_layers.py
plone/app/testing/tests.py
plone/app/testing/utils.py
plone/app/testing/profile/metadata.xml
plone_app_testing-7.1.2.dist-info/METADATA
plone_app_testing-7.1.2.dist-info/WHEEL
plone_app_testing-7.1.2.dist-info/namespace_packages.txt
plone_app_testing-7.1.2.dist-info/top_level.txt
plone_app_testing-7.1.2.dist-info/RECORD
