Metadata-Version: 2.4
Name: plone.app.testing
Version: 7.1.2
Summary: Testing tools for Plone-the-application, based on plone.testing.
Home-page: https://pypi.org/project/plone.app.testing
Author: Plone Foundation
Author-email: plone-developers@lists.sourceforge.net
License: GPL version 2
Keywords: plone tests
Classifier: Development Status :: 5 - Production/Stable
Classifier: Environment :: Web Environment
Classifier: Framework :: Plone
Classifier: Framework :: Plone :: 6.0
Classifier: Framework :: Plone :: 6.1
Classifier: Framework :: Plone :: Core
Classifier: Framework :: Zope :: 4
Classifier: Framework :: Zope :: 5
Classifier: License :: OSI Approved :: GNU General Public License v2 (GPLv2)
Classifier: Operating System :: OS Independent
Classifier: Programming Language :: Python
Classifier: Programming Language :: Python :: 3.8
Classifier: Programming Language :: Python :: 3.9
Classifier: Programming Language :: Python :: 3.10
Classifier: Programming Language :: Python :: 3.11
Classifier: Programming Language :: Python :: 3.12
Classifier: Programming Language :: Python :: 3.13
Classifier: Topic :: Internet :: WWW/HTTP :: Dynamic Content
Requires-Python: >=3.8
Requires-Dist: Products.CMFPlone
Requires-Dist: Products.GenericSetup
Requires-Dist: Products.MailHost
Requires-Dist: Products.PluggableAuthService
Requires-Dist: Zope
Requires-Dist: persistent
Requires-Dist: plone.app.contenttypes
Requires-Dist: plone.dexterity
Requires-Dist: plone.memoize
Requires-Dist: plone.registry
Requires-Dist: plone.testing[security,zca,zodb]
Requires-Dist: setuptools
Requires-Dist: zope.configuration
Requires-Dist: zope.component
Requires-Dist: zope.dottedname
Requires-Dist: zope.testing
Provides-Extra: test
Requires-Dist: plone.testing[test]; extra == "test"
Requires-Dist: Products.CMFPlone; extra == "test"
Requires-Dist: Products.PluggableAuthService; extra == "test"
Requires-Dist: requests; extra == "test"
Requires-Dist: transaction; extra == "test"
Requires-Dist: zope.interface; extra == "test"
Requires-Dist: zope.testing; extra == "test"
Requires-Dist: zope.testrunner; extra == "test"
Provides-Extra: robot
Requires-Dist: robotsuite>=1.4.0; extra == "robot"
Requires-Dist: robotframework-selenium2library; extra == "robot"
Requires-Dist: decorator; extra == "robot"
Requires-Dist: selenium; extra == "robot"
Dynamic: author
Dynamic: author-email
Dynamic: classifier
Dynamic: description
Dynamic: description-content-type
Dynamic: home-page
Dynamic: keywords
Dynamic: license
Dynamic: provides-extra
Dynamic: requires-dist
Dynamic: requires-python
Dynamic: summary
